i3configger/__init__.py
i3configger/__main__.py
i3configger/base.py
i3configger/bindings.py
i3configger/build.py
i3configger/cli.py
i3configger/config.py
i3configger/context.py
i3configger/exc.py
i3configger/inotify_simple.py
i3configger/ipc.py
i3configger/message.py
i3configger/partials.py
i3configger/watch.py
i3configger-0.9.1.post1.dist-info/LICENSE
i3configger-0.9.1.post1.dist-info/METADATA
i3configger-0.9.1.post1.dist-info/WHEEL
i3configger-0.9.1.post1.dist-info/entry_points.txt
i3configger-0.9.1.post1.dist-info/top_level.txt
i3configger-0.9.1.post1.dist-info/RECORD
