Metadata-Version: 2.1
Name: i3configger
Version: 0.9.1.post1
Summary: i3 config manipulation tool
Home-page: https://github.com/obestwalter/i3configger
Author: Oliver Bestwalter
License: UNKNOWN
Platform: UNKNOWN
Classifier: Development Status :: 4 - Beta
Classifier: Operating System :: POSIX :: Linux
Classifier: License :: OSI Approved :: MIT License
Classifier: Environment :: Console
Classifier: Topic :: Utilities
Classifier: Programming Language :: Python
Classifier: Programming Language :: Python :: 3.6
Classifier: Programming Language :: Python :: 3.7
Requires-Python: >=3.6
Requires-Dist: psutil
Requires-Dist: python-daemon
Provides-Extra: docs
Requires-Dist: mkdocs ; extra == 'docs'
Requires-Dist: mkdocs-material ; extra == 'docs'
Provides-Extra: lint
Requires-Dist: pre-commit ; extra == 'lint'
Provides-Extra: release
Requires-Dist: plumbum ; extra == 'release'
Requires-Dist: twine ; extra == 'release'
Requires-Dist: readme-renderer[md] ; extra == 'release'
Provides-Extra: test
Requires-Dist: pytest ; extra == 'test'
